{
	"status": "success",
	"title": "Tawny.ai Launch Campaign",
	"link": "tawny-ai-launch-campaign.html.html",
	"content": "TAWNY.ai is a pioneer in the field of modern, AI-powered emotion detection technology. Their vision is to democratise emotion AI, making it accessible to all. They came to our team at Hyper Island, wanted help with creating a roll out plan for TAWNY Live, a new tool which analyses human emotions in real time, bringing the human element to virtual meetings.",
	"date_finish": "<span class=\"atail-project-date\"><span class=\"atail-proj-date-text\">Finished </span><span class=\"atail-proj-date-value\">- 16 Jun 2021</span></span>",
	"date_start": "<span class=\"atail-project-date\"><span class=\"atail-proj-date-text\">Started </span><span class=\"atail-proj-date-value\">- 15 May 2021</span></span>",
	"thumbnail": "<img width=\"1200\" height=\"911\" src=\"img/hubista.png\" alt=\"pexels-photo-69494\" />",
	"thumbnail_url": "img/hubista.png",
	"token": "865fc8f5ec",
	"slides": [
		{
			"src": {
				"img": "img/tawny/style.png",
				"title": "Mr Neely",
				"text": "Mr Neely",
				"fit": "cover"
			},
			"fit": "cover",
			"type": "image"
		}
	]
}